<MusicList>
    <Music>
        <title>[MV] Zico - Tough Cookie</title>
        <id>P2RLb-RryEs</id>
    </Music>
    <Music>
        <title>[MV] Zico - Well Done</title>
        <id>eXzYHR4zb2A</id>
    </Music>
    <Music>
        <title>[MV] Jamezz, Andup, Mino - 거북선</title>
        <id>amPsxN0ZWP8</id>
    </Music>
    <Music>
        <title>[Audio] Incredible, Tablo, Jinusean - 오빠차</title>
        <id>c9V7nIbcPFw</id>
    </Music>
    <Music>
        <title>[Audio] SuperB, Tablo, Jinusean - 아빠차</title>
        <id>Vb3gwdeaf1g</id>
    </Music>
    <Music>
        <title>[MV] Black Nut, Micro Dot, Basick - My Zone</title>
        <id>dA7tGKLVjY0</id>
    </Music>
    <Music>
        <title>[MV] Sik-K, Lil Boi, 지구인 - RESPECT</title>
        <id>EADYw_ku3hE</id>
    </Music>
    <Music>
        <title>[Audio] Mino, Zico, Paloalto - Moneyflow</title>
        <id>d_5V7krsbmk</id>
    </Music>
    <Music>
        <title>[MV] Bluck Nut, Verbal Jint, SanE - M.I.L.E</title>
        <id>s6PuFmtOAZM</id>
    </Music>
    <Music>
        <title>[Audio] Innovator, Incredible, SuperB - OG</title>
        <id>QDL3rUz8sXQ</id>
    </Music>
    <Music>
        <title>[MV] Innovator - More than a TV Star</title>
        <id>lKosin6hERk</id>
    </Music>
    <Music>
        <title>[MV] Basick - GXNZI</title>
        <id>73nblx8CAtM</id>
    </Music>
    <Music>
        <title>[MV] Ril Boi, Loco, Jay Park - ON IT + BO$$</title>
        <id>_Y2frkeH9fo</id>
    </Music>
    <Music>
        <title>[Audio] Black Nut - Higher Than E-Sens</title>
        <id>yIfnoB_rgLE</id>
    </Music>
    <Music>
        <title>[Audio] Black Nut - Baechigi</title>
        <id>tYG3odcCklA</id>
    </Music>
    <Music>
        <title>[Audio] Black Nut, JOOHEON - ㄴㄴ</title>
        <id>r6aAU1iSNeY</id>
    </Music>
    <Music>
        <title>[Audio] Black Nut - 100</title>
        <id>X2KmhMmqj_A</id>
    </Music>
    <Music>
        <title>[Audio] Black Nut - Beenzino</title>
        <id>5WivimIJDr0</id>
    </Music>
    <Music>
        <title>[Audio] Black Nut - Last Friday Night</title>
        <id>BQ41zYjQwaA</id>
    </Music>
    <Music>
        <title>[MV] SanE - Me You</title>
        <id>nUYu7SFzhBQ</id>
    </Music>
    <Music>
        <title>[MV] SanE - Body Language</title>
        <id>8kdQmd5CNN4</id>
    </Music>
    <Music>
        <title>[MV] SanE - Break Up Dinner</title>
        <id>3FowjIBQms4</id>
    </Music>
    <Music>
        <title>[MV] SanE - On Top of Your Head</title>
        <id>PCtJSWk4sdA</id>
    </Music>
    <Music>
        <title>[MV] SanE, Raina - A midsummer Night's Sweetness</title>
        <id>nkfMN-jaycA</id>
    </Music>
    <Music>
        <title>[MV] SanE - Story of someone I know</title>
        <id>eVdjb3AtKpM</id>
    </Music>
    <Music>
        <title>[MV] SanE - Rap Circus</title>
        <id>sNsrl6tTMAI</id>
    </Music>
    <Music>
        <title>[MV] SanE - Where Did You Sleep</title>
        <id>Ve7ZWkXvdPU</id>
    </Music>
    <Music>
        <title>[Audio] SanE - Wish You To Be Unhappy</title>
        <id>iTKMTTkSpzc</id>
    </Music>
    <Music>
        <title>[MV] SanE - What's Wrong With Me</title>
        <id>ywVZh_b7MWQ</id>
    </Music>
    <Music>
        <title>[MV] Tablo - Eyes, Nose, Lips</title>
        <id>qhc_UpS6U3Y</id>
    </Music>
    <Music>
        <title>[MV] Epik High - Born Hater</title>
        <id>3s1jaFDrp5M</id>
    </Music>
    <Music>
        <title>[MV] Loco - Respect</title>
        <id>qSPHD6zAS8I</id>
    </Music>
    <Music>
        <title>[MV] Loco - High</title>
        <id>mdJ0QlsfcWY</id>
    </Music>
    <Music>
        <title>[MV] Loco - Thinking about you</title>
        <id>ghJ3hC5N7-Y</id>
    </Music>
    <Music>
        <title>[MV] Loco - Hold Me Tight</title>
        <id>JuCqkpgA1p0</id>
    </Music>
    <Music>
        <title>[MV] Loco, 유주 - 우연히 봄</title>
        <id>v3FWSaUk5HE</id>
    </Music>
    <Music>
        <title>[Audio] Loco - Awesome</title>
        <id>Jbrvq4F2J4Q</id>
    </Music>
    <Music>
        <title>[Audio] Loco - No Manners</title>
        <id>9dCu5bV2ib4</id>
    </Music>
    <Music>
        <title>[Audio] Gray - Just Do It</title>
        <id>DHISHWPkSEA</id>
    </Music>
</MusicList>

